Metadata-Version: 1.1
Name: apkdl
Version: 1.0.0
Summary: Search and download APKs from the command line
Home-page: https://github.com/sereneblue/apkdl
Author: sereneblue
Author-email: UNKNOWN
License: MIT
Keywords: android,apk,cli
Platform: UNKNOWN
Classifier: Intended Audience :: Developers
Classifier: Environment :: Console
Classifier: Topic :: Utilities
Classifier: License :: OSI Approved :: MIT License
Classifier: Natural Language :: English
Classifier: Operating System :: OS Independent
Classifier: Programming Language :: Python :: 3
Classifier: Programming Language :: Python :: 3.2
Classifier: Programming Language :: Python :: 3.3
Classifier: Programming Language :: Python :: 3.4
Classifier: Programming Language :: Python :: 3.5
Classifier: Programming Language :: Python :: 3.6
